fractionalindex/__init__.py
fractionalindex/fractionalindex.py
fractionalindex-0.0.2.dist-info/LICENSE
fractionalindex-0.0.2.dist-info/METADATA
fractionalindex-0.0.2.dist-info/WHEEL
fractionalindex-0.0.2.dist-info/top_level.txt
fractionalindex-0.0.2.dist-info/RECORD
