Metadata-Version: 2.1
Name: fractionalindex
Version: 0.0.2
Summary: Fractional index library with multiple backends
Author: Jeremy Howard
Classifier: Programming Language :: Python :: 3
Classifier: License :: OSI Approved :: Apache Software License
Classifier: Operating System :: OS Independent
Requires-Python: >=3.9
License-File: LICENSE
Requires-Dist: sortedcontainers
Requires-Dist: fractional_indexing
Provides-Extra: test
Requires-Dist: pytest; extra == "test"
